{
  "manifestVersion": "3.2",
  "proxies": [
    {
      "address": "0x9DbAc805e4b9FfB35298fA55E7cdcd65645314a6",
      "txHash": "0xf40bab245914e56eebfd1af26c9d4638a9569101bfdd7c76648b5ca0b0452743",
      "kind": "uups"
    },
    {
      "address": "0xfFD890eBB19277f59f9d0810D464Efd2775df08E",
      "txHash": "0x27393062d33b80510907f63c97c9005e64bba1687df6580719028f933be6a05c",
      "kind": "uups"
    }
  ],
  "impls": {
    "11750c0ff569164e6cbab51ad18a6d79b648024811385c551088f77a3cae2b6f": {
      "address": "0x26C1FC685E9A39D00A34e731CAf1BEBA71C4EE61",
      "txHash": "0xd3f7b647ff26d47b7fbd7d0b215653a1a96752b720a3648c76325f64239627f7",
      "layout": {
        "solcVersion": "0.8.18",
        "storage": [
          {
            "label": "_initialized",
            "offset": 0,
            "slot": "0",
            "type": "t_uint8",
            "contract": "Initializable",
            "src": "@openzeppelin/contracts-upgradeable/proxy/utils/Initializable.sol:63",
            "retypedFrom": "bool"
          },
          {
            "label": "_initializing",
            "offset": 1,
            "slot": "0",
            "type": "t_bool",
            "contract": "Initializable",
            "src": "@openzeppelin/contracts-upgradeable/proxy/utils/Initializable.sol:68"
          },
          {
            "label": "__gap",
            "offset": 0,
            "slot": "1",
            "type": "t_array(t_uint256)50_storage",
            "contract": "ContextUpgradeable",
            "src": "@openzeppelin/contracts-upgradeable/utils/ContextUpgradeable.sol:36"
          },
          {
            "label": "__gap",
            "offset": 0,
            "slot": "51",
            "type": "t_array(t_uint256)50_storage",
            "contract": "ERC165Upgradeable",
            "src": "@openzeppelin/contracts-upgradeable/utils/introspection/ERC165Upgradeable.sol:41"
          },
          {
            "label": "_name",
            "offset": 0,
            "slot": "101",
            "type": "t_string_storage",
            "contract": "ERC721Upgradeable",
            "src": "@openzeppelin/contracts-upgradeable/token/ERC721/ERC721Upgradeable.sol:25"
          },
          {
            "label": "_symbol",
            "offset": 0,
            "slot": "102",
            "type": "t_string_storage",
            "contract": "ERC721Upgradeable",
            "src": "@openzeppelin/contracts-upgradeable/token/ERC721/ERC721Upgradeable.sol:28"
          },
          {
            "label": "_owners",
            "offset": 0,
            "slot": "103",
            "type": "t_mapping(t_uint256,t_address)",
            "contract": "ERC721Upgradeable",
            "src": "@openzeppelin/contracts-upgradeable/token/ERC721/ERC721Upgradeable.sol:31"
          },
          {
            "label": "_balances",
            "offset": 0,
            "slot": "104",
            "type": "t_mapping(t_address,t_uint256)",
            "contract": "ERC721Upgradeable",
            "src": "@openzeppelin/contracts-upgradeable/token/ERC721/ERC721Upgradeable.sol:34"
          },
          {
            "label": "_tokenApprovals",
            "offset": 0,
            "slot": "105",
            "type": "t_mapping(t_uint256,t_address)",
            "contract": "ERC721Upgradeable",
            "src": "@openzeppelin/contracts-upgradeable/token/ERC721/ERC721Upgradeable.sol:37"
          },
          {
            "label": "_operatorApprovals",
            "offset": 0,
            "slot": "106",
            "type": "t_mapping(t_address,t_mapping(t_address,t_bool))",
            "contract": "ERC721Upgradeable",
            "src": "@openzeppelin/contracts-upgradeable/token/ERC721/ERC721Upgradeable.sol:40"
          },
          {
            "label": "__gap",
            "offset": 0,
            "slot": "107",
            "type": "t_array(t_uint256)44_storage",
            "contract": "ERC721Upgradeable",
            "src": "@openzeppelin/contracts-upgradeable/token/ERC721/ERC721Upgradeable.sol:477"
          },
          {
            "label": "_tokenURIs",
            "offset": 0,
            "slot": "151",
            "type": "t_mapping(t_uint256,t_string_storage)",
            "contract": "ERC721URIStorageUpgradeable",
            "src": "@openzeppelin/contracts-upgradeable/token/ERC721/extensions/ERC721URIStorageUpgradeable.sol:22"
          },
          {
            "label": "__gap",
            "offset": 0,
            "slot": "152",
            "type": "t_array(t_uint256)49_storage",
            "contract": "ERC721URIStorageUpgradeable",
            "src": "@openzeppelin/contracts-upgradeable/token/ERC721/extensions/ERC721URIStorageUpgradeable.sol:86"
          },
          {
            "label": "_paused",
            "offset": 0,
            "slot": "201",
            "type": "t_bool",
            "contract": "PausableUpgradeable",
            "src": "@openzeppelin/contracts-upgradeable/security/PausableUpgradeable.sol:29"
          },
          {
            "label": "__gap",
            "offset": 0,
            "slot": "202",
            "type": "t_array(t_uint256)49_storage",
            "contract": "PausableUpgradeable",
            "src": "@openzeppelin/contracts-upgradeable/security/PausableUpgradeable.sol:116"
          },
          {
            "label": "_roles",
            "offset": 0,
            "slot": "251",
            "type": "t_mapping(t_bytes32,t_struct(RoleData)34_storage)",
            "contract": "AccessControlUpgradeable",
            "src": "@openzeppelin/contracts-upgradeable/access/AccessControlUpgradeable.sol:62"
          },
          {
            "label": "__gap",
            "offset": 0,
            "slot": "252",
            "type": "t_array(t_uint256)49_storage",
            "contract": "AccessControlUpgradeable",
            "src": "@openzeppelin/contracts-upgradeable/access/AccessControlUpgradeable.sol:260"
          },
          {
            "label": "__gap",
            "offset": 0,
            "slot": "301",
            "type": "t_array(t_uint256)50_storage",
            "contract": "ERC721BurnableUpgradeable",
            "src": "@openzeppelin/contracts-upgradeable/token/ERC721/extensions/ERC721BurnableUpgradeable.sol:38"
          },
          {
            "label": "__gap",
            "offset": 0,
            "slot": "351",
            "type": "t_array(t_uint256)50_storage",
            "contract": "ERC1967UpgradeUpgradeable",
            "src": "@openzeppelin/contracts-upgradeable/proxy/ERC1967/ERC1967UpgradeUpgradeable.sol:169"
          },
          {
            "label": "__gap",
            "offset": 0,
            "slot": "401",
            "type": "t_array(t_uint256)50_storage",
            "contract": "UUPSUpgradeable",
            "src": "@openzeppelin/contracts-upgradeable/proxy/utils/UUPSUpgradeable.sol:111"
          },
          {
            "label": "batchIds",
            "offset": 0,
            "slot": "451",
            "type": "t_array(t_uint256)dyn_storage",
            "contract": "BatchMintMetadata",
            "src": "@thirdweb-dev/contracts/extension/BatchMintMetadata.sol:15"
          },
          {
            "label": "baseURI",
            "offset": 0,
            "slot": "452",
            "type": "t_mapping(t_uint256,t_string_storage)",
            "contract": "BatchMintMetadata",
            "src": "@thirdweb-dev/contracts/extension/BatchMintMetadata.sol:18"
          },
          {
            "label": "nextTokenIdToLazyMint",
            "offset": 0,
            "slot": "453",
            "type": "t_uint256",
            "contract": "LazyMint",
            "src": "@thirdweb-dev/contracts/extension/LazyMint.sol:17"
          },
          {
            "label": "claimCondition",
            "offset": 0,
            "slot": "454",
            "type": "t_struct(ClaimCondition)7355_storage",
            "contract": "DropSinglePhase",
            "src": "@thirdweb-dev/contracts/extension/DropSinglePhase.sol:15"
          },
          {
            "label": "conditionId",
            "offset": 0,
            "slot": "462",
            "type": "t_bytes32",
            "contract": "DropSinglePhase",
            "src": "@thirdweb-dev/contracts/extension/DropSinglePhase.sol:18"
          },
          {
            "label": "supplyClaimedByWallet",
            "offset": 0,
            "slot": "463",
            "type": "t_mapping(t_bytes32,t_mapping(t_address,t_uint256))",
            "contract": "DropSinglePhase",
            "src": "@thirdweb-dev/contracts/extension/DropSinglePhase.sol:27"
          },
          {
            "label": "_tokenIdCounter",
            "offset": 0,
            "slot": "464",
            "type": "t_struct(Counter)4424_storage",
            "contract": "BionicInvestorPass",
            "src": "contracts/BIP.sol:32"
          },
          {
            "label": "platformFeeRecipient",
            "offset": 0,
            "slot": "465",
            "type": "t_address",
            "contract": "BionicInvestorPass",
            "src": "contracts/BIP.sol:34"
          }
        ],
        "types": {
          "t_address": {
            "label": "address",
            "numberOfBytes": "20"
          },
          "t_array(t_uint256)44_storage": {
            "label": "uint256[44]",
            "numberOfBytes": "1408"
          },
          "t_array(t_uint256)49_storage": {
            "label": "uint256[49]",
            "numberOfBytes": "1568"
          },
          "t_array(t_uint256)50_storage": {
            "label": "uint256[50]",
            "numberOfBytes": "1600"
          },
          "t_array(t_uint256)dyn_storage": {
            "label": "uint256[]",
            "numberOfBytes": "32"
          },
          "t_bool": {
            "label": "bool",
            "numberOfBytes": "1"
          },
          "t_bytes32": {
            "label": "bytes32",
            "numberOfBytes": "32"
          },
          "t_mapping(t_address,t_bool)": {
            "label": "mapping(address => bool)",
            "numberOfBytes": "32"
          },
          "t_mapping(t_address,t_mapping(t_address,t_bool))": {
            "label": "mapping(address => mapping(address => bool))",
            "numberOfBytes": "32"
          },
          "t_mapping(t_address,t_uint256)": {
            "label": "mapping(address => uint256)",
            "numberOfBytes": "32"
          },
          "t_mapping(t_bytes32,t_mapping(t_address,t_uint256))": {
            "label": "mapping(bytes32 => mapping(address => uint256))",
            "numberOfBytes": "32"
          },
          "t_mapping(t_bytes32,t_struct(RoleData)34_storage)": {
            "label": "mapping(bytes32 => struct AccessControlUpgradeable.RoleData)",
            "numberOfBytes": "32"
          },
          "t_mapping(t_uint256,t_address)": {
            "label": "mapping(uint256 => address)",
            "numberOfBytes": "32"
          },
          "t_mapping(t_uint256,t_string_storage)": {
            "label": "mapping(uint256 => string)",
            "numberOfBytes": "32"
          },
          "t_string_storage": {
            "label": "string",
            "numberOfBytes": "32"
          },
          "t_struct(ClaimCondition)7355_storage": {
            "label": "struct IClaimCondition.ClaimCondition",
            "members": [
              {
                "label": "startTimestamp",
                "type": "t_uint256",
                "offset": 0,
                "slot": "0"
              },
              {
                "label": "maxClaimableSupply",
                "type": "t_uint256",
                "offset": 0,
                "slot": "1"
              },
              {
                "label": "supplyClaimed",
                "type": "t_uint256",
                "offset": 0,
                "slot": "2"
              },
              {
                "label": "quantityLimitPerWallet",
                "type": "t_uint256",
                "offset": 0,
                "slot": "3"
              },
              {
                "label": "merkleRoot",
                "type": "t_bytes32",
                "offset": 0,
                "slot": "4"
              },
              {
                "label": "pricePerToken",
                "type": "t_uint256",
                "offset": 0,
                "slot": "5"
              },
              {
                "label": "currency",
                "type": "t_address",
                "offset": 0,
                "slot": "6"
              },
              {
                "label": "metadata",
                "type": "t_string_storage",
                "offset": 0,
                "slot": "7"
              }
            ],
            "numberOfBytes": "256"
          },
          "t_struct(Counter)4424_storage": {
            "label": "struct CountersUpgradeable.Counter",
            "members": [
              {
                "label": "_value",
                "type": "t_uint256",
                "offset": 0,
                "slot": "0"
              }
            ],
            "numberOfBytes": "32"
          },
          "t_struct(RoleData)34_storage": {
            "label": "struct AccessControlUpgradeable.RoleData",
            "members": [
              {
                "label": "members",
                "type": "t_mapping(t_address,t_bool)",
                "offset": 0,
                "slot": "0"
              },
              {
                "label": "adminRole",
                "type": "t_bytes32",
                "offset": 0,
                "slot": "1"
              }
            ],
            "numberOfBytes": "64"
          },
          "t_uint256": {
            "label": "uint256",
            "numberOfBytes": "32"
          },
          "t_uint8": {
            "label": "uint8",
            "numberOfBytes": "1"
          }
        }
      }
    }
  }
}
